MANIFEST.in
README.md
setup.py
activity/__init__.py
activity/admin.py
activity/apps.py
activity/managers.py
activity/models.py
activity/registry.py
activity/signals.py
activity/tasks.py
activity/tests.py
activity/views.py
activity/migrations/0001_initial.py
activity/migrations/0002_auto_20170504_1348.py
activity/migrations/__init__.py
activity/templates/activity/item.html
django_activity.egg-info/PKG-INFO
django_activity.egg-info/SOURCES.txt
django_activity.egg-info/dependency_links.txt
django_activity.egg-info/requires.txt
django_activity.egg-info/top_level.txt