Metadata-Version: 1.0
Name: django-activity
Version: 0.6.3
Summary: Django Activity provides support for streams
Home-page: http://github.com/eofs/django-activity
Author: Tomi Pajunen
Author-email: tomi@madlab.fi
License: BSD
Platform: UNKNOWN
